[
  {
    "id": 140808,
    "province_id": 14,
    "regency_id": 1408,
    "value": "Bunga Raya"
  },
  {
    "id": 140806,
    "province_id": 14,
    "regency_id": 1408,
    "value": "Dayun"
  },
  {
    "id": 140810,
    "province_id": 14,
    "regency_id": 1408,
    "value": "Kandis"
  },
  {
    "id": 140807,
    "province_id": 14,
    "regency_id": 1408,
    "value": "Kerinci Kanan"
  },
  {
    "id": 140809,
    "province_id": 14,
    "regency_id": 1408,
    "value": "Koto Gasib"
  },
  {
    "id": 140811,
    "province_id": 14,
    "regency_id": 1408,
    "value": "Lubuk Dalam"
  },
  {
    "id": 140813,
    "province_id": 14,
    "regency_id": 1408,
    "value": "Mempura"
  },
  {
    "id": 140803,
    "province_id": 14,
    "regency_id": 1408,
    "value": "Minas"
  },
  {
    "id": 140814,
    "province_id": 14,
    "regency_id": 1408,
    "value": "Pusako"
  },
  {
    "id": 140812,
    "province_id": 14,
    "regency_id": 1408,
    "value": "Sabak Auh"
  },
  {
    "id": 140801,
    "province_id": 14,
    "regency_id": 1408,
    "value": "Siak"
  },
  {
    "id": 140802,
    "province_id": 14,
    "regency_id": 1408,
    "value": "Sungai Apit"
  },
  {
    "id": 140805,
    "province_id": 14,
    "regency_id": 1408,
    "value": "Sungai Mandau"
  },
  {
    "id": 140804,
    "province_id": 14,
    "regency_id": 1408,
    "value": "Tualang"
  }
]