[
  {
    "id": 3171021004,
    "province_id": 31,
    "regency_id": 3171,
    "district_id": 317102,
    "value": "Gunung Sahari Utara",
    "postal_code": "10720"
  },
  {
    "id": 3171021002,
    "province_id": 31,
    "regency_id": 3171,
    "district_id": 317102,
    "value": "Karang Anyar",
    "postal_code": "10740"
  },
  {
    "id": 3171021003,
    "province_id": 31,
    "regency_id": 3171,
    "district_id": 317102,
    "value": "Kartini",
    "postal_code": "10750"
  },
  {
    "id": 3171021005,
    "province_id": 31,
    "regency_id": 3171,
    "district_id": 317102,
    "value": "Mangga Dua Selatan",
    "postal_code": "10730"
  },
  {
    "id": 3171021001,
    "province_id": 31,
    "regency_id": 3171,
    "district_id": 317102,
    "value": "Pasar Baru",
    "postal_code": "10710"
  }
]