[
  {
    "id": 3506042009,
    "province_id": 35,
    "regency_id": 3506,
    "district_id": 350604,
    "value": "Badal",
    "postal_code": "64171"
  },
  {
    "id": 3506042010,
    "province_id": 35,
    "regency_id": 3506,
    "district_id": 350604,
    "value": "Badal Pandean (Badalpandean)",
    "postal_code": "64171"
  },
  {
    "id": 3506042003,
    "province_id": 35,
    "regency_id": 3506,
    "district_id": 350604,
    "value": "Banggle",
    "postal_code": "64171"
  },
  {
    "id": 3506042015,
    "province_id": 35,
    "regency_id": 3506,
    "district_id": 350604,
    "value": "Banjarejo",
    "postal_code": "64171"
  },
  {
    "id": 3506042013,
    "province_id": 35,
    "regency_id": 3506,
    "district_id": 350604,
    "value": "Bedug",
    "postal_code": "64171"
  },
  {
    "id": 3506042004,
    "province_id": 35,
    "regency_id": 3506,
    "district_id": 350604,
    "value": "Branggahan",
    "postal_code": "64171"
  },
  {
    "id": 3506042006,
    "province_id": 35,
    "regency_id": 3506,
    "district_id": 350604,
    "value": "Dukuh",
    "postal_code": "64171"
  },
  {
    "id": 3506042014,
    "province_id": 35,
    "regency_id": 3506,
    "district_id": 350604,
    "value": "Mangunrejo",
    "postal_code": "64171"
  },
  {
    "id": 3506042008,
    "province_id": 35,
    "regency_id": 3506,
    "district_id": 350604,
    "value": "Ngadiluwih",
    "postal_code": "64171"
  },
  {
    "id": 3506042007,
    "province_id": 35,
    "regency_id": 3506,
    "district_id": 350604,
    "value": "Purwokerto",
    "postal_code": "64171"
  },
  {
    "id": 3506042011,
    "province_id": 35,
    "regency_id": 3506,
    "district_id": 350604,
    "value": "Rembang",
    "postal_code": "64171"
  },
  {
    "id": 3506042012,
    "province_id": 35,
    "regency_id": 3506,
    "district_id": 350604,
    "value": "Rembangkepuh",
    "postal_code": "64171"
  },
  {
    "id": 3506042002,
    "province_id": 35,
    "regency_id": 3506,
    "district_id": 350604,
    "value": "Seketi",
    "postal_code": "64171"
  },
  {
    "id": 3506042005,
    "province_id": 35,
    "regency_id": 3506,
    "district_id": 350604,
    "value": "Slumbung",
    "postal_code": "64171"
  },
  {
    "id": 3506042001,
    "province_id": 35,
    "regency_id": 3506,
    "district_id": 350604,
    "value": "Tales",
    "postal_code": "64171"
  },
  {
    "id": 3506042016,
    "province_id": 35,
    "regency_id": 3506,
    "district_id": 350604,
    "value": "Wonorejo",
    "postal_code": "64171"
  }
]