[
  {
    "id": 6503172009,
    "province_id": 65,
    "regency_id": 6503,
    "district_id": 650317,
    "value": "Ba' Liku (Ba Liku)",
    "postal_code": "77458"
  },
  {
    "id": 6503172006,
    "province_id": 65,
    "regency_id": 6503,
    "district_id": 650317,
    "value": "Binuang",
    "postal_code": "77458"
  },
  {
    "id": 6503172003,
    "province_id": 65,
    "regency_id": 6503,
    "district_id": 650317,
    "value": "Long Kelupan",
    "postal_code": "77458"
  },
  {
    "id": 6503172007,
    "province_id": 65,
    "regency_id": 6503,
    "district_id": 650317,
    "value": "Long Mutan",
    "postal_code": "77458"
  },
  {
    "id": 6503172004,
    "province_id": 65,
    "regency_id": 6503,
    "district_id": 650317,
    "value": "Long Padi",
    "postal_code": "77458"
  },
  {
    "id": 6503172010,
    "province_id": 65,
    "regency_id": 6503,
    "district_id": 650317,
    "value": "Long Rian",
    "postal_code": "77458"
  },
  {
    "id": 6503172002,
    "province_id": 65,
    "regency_id": 6503,
    "district_id": 650317,
    "value": "Long Rungan",
    "postal_code": "77458"
  },
  {
    "id": 6503172008,
    "province_id": 65,
    "regency_id": 6503,
    "district_id": 650317,
    "value": "Pa' Milau (Pa Milau)",
    "postal_code": "77458"
  },
  {
    "id": 6503172011,
    "province_id": 65,
    "regency_id": 6503,
    "district_id": 650317,
    "value": "Pa' Yalau (Pa Yalau)",
    "postal_code": "77458"
  },
  {
    "id": 6503172005,
    "province_id": 65,
    "regency_id": 6503,
    "district_id": 650317,
    "value": "Tang Badui",
    "postal_code": "77458"
  },
  {
    "id": 6503172001,
    "province_id": 65,
    "regency_id": 6503,
    "district_id": 650317,
    "value": "Tang Paye",
    "postal_code": "77458"
  }
]