[
  {
    "id": 6209032037,
    "province_id": 62,
    "regency_id": 6209,
    "district_id": 620903,
    "value": "Arga Mulya (Argo Mulyo)",
    "postal_code": "74162"
  },
  {
    "id": 6209032003,
    "province_id": 62,
    "regency_id": 6209,
    "district_id": 620903,
    "value": "Batu Kotam",
    "postal_code": "74162"
  },
  {
    "id": 6209032007,
    "province_id": 62,
    "regency_id": 6209,
    "district_id": 620903,
    "value": "Beruta (Baruta)",
    "postal_code": "74162"
  },
  {
    "id": 6209032036,
    "province_id": 62,
    "regency_id": 6209,
    "district_id": 620903,
    "value": "Bukit Indah",
    "postal_code": "74162"
  },
  {
    "id": 6209032031,
    "province_id": 62,
    "regency_id": 6209,
    "district_id": 620903,
    "value": "Bumi Agung",
    "postal_code": "74162"
  },
  {
    "id": 6209032006,
    "province_id": 62,
    "regency_id": 6209,
    "district_id": 620903,
    "value": "Bunut",
    "postal_code": "74162"
  },
  {
    "id": 6209032002,
    "province_id": 62,
    "regency_id": 6209,
    "district_id": 620903,
    "value": "Guci",
    "postal_code": "74162"
  },
  {
    "id": 6209032004,
    "province_id": 62,
    "regency_id": 6209,
    "district_id": 620903,
    "value": "Kujan",
    "postal_code": "74612"
  },
  {
    "id": 6209031005,
    "province_id": 62,
    "regency_id": 6209,
    "district_id": 620903,
    "value": "Nanga Bulik",
    "postal_code": "74611"
  },
  {
    "id": 6209032044,
    "province_id": 62,
    "regency_id": 6209,
    "district_id": 620903,
    "value": "Nanga Pamalontian",
    "postal_code": "74162"
  },
  {
    "id": 6209032043,
    "province_id": 62,
    "regency_id": 6209,
    "district_id": 620903,
    "value": "Perigi Raya",
    "postal_code": "74162"
  },
  {
    "id": 6209032032,
    "province_id": 62,
    "regency_id": 6209,
    "district_id": 620903,
    "value": "Sumber Mulya",
    "postal_code": "74162"
  },
  {
    "id": 6209032001,
    "province_id": 62,
    "regency_id": 6209,
    "district_id": 620903,
    "value": "Sungai Mentawa",
    "postal_code": "74162"
  },
  {
    "id": 6209032008,
    "province_id": 62,
    "regency_id": 6209,
    "district_id": 620903,
    "value": "Tamiang",
    "postal_code": "74162"
  }
]