[
  {
    "id": 117101,
    "province_id": 11,
    "regency_id": 1171,
    "value": "Baiturrahman"
  },
  {
    "id": 117107,
    "province_id": 11,
    "regency_id": 1171,
    "value": "Banda Raya"
  },
  {
    "id": 117108,
    "province_id": 11,
    "regency_id": 1171,
    "value": "Jaya Baru"
  },
  {
    "id": 117102,
    "province_id": 11,
    "regency_id": 1171,
    "value": "Kuta Alam"
  },
  {
    "id": 117106,
    "province_id": 11,
    "regency_id": 1171,
    "value": "Kuta Raja"
  },
  {
    "id": 117105,
    "province_id": 11,
    "regency_id": 1171,
    "value": "Lueng Bata"
  },
  {
    "id": 117103,
    "province_id": 11,
    "regency_id": 1171,
    "value": "Meuraxa"
  },
  {
    "id": 117104,
    "province_id": 11,
    "regency_id": 1171,
    "value": "Syiah Kuala"
  },
  {
    "id": 117109,
    "province_id": 11,
    "regency_id": 1171,
    "value": "Ulee Kareng"
  }
]