[
  {
    "id": 3310042010,
    "province_id": 33,
    "regency_id": 3310,
    "district_id": 331004,
    "value": "Banyuripan",
    "postal_code": "57462"
  },
  {
    "id": 3310042009,
    "province_id": 33,
    "regency_id": 3310,
    "district_id": 331004,
    "value": "Beluk",
    "postal_code": "57462"
  },
  {
    "id": 3310042006,
    "province_id": 33,
    "regency_id": 3310,
    "district_id": 331004,
    "value": "Bogem",
    "postal_code": "57462"
  },
  {
    "id": 3310042003,
    "province_id": 33,
    "regency_id": 3310,
    "district_id": 331004,
    "value": "Dukuh",
    "postal_code": "57462"
  },
  {
    "id": 3310042011,
    "province_id": 33,
    "regency_id": 3310,
    "district_id": 331004,
    "value": "Gununggajah (Gunung Gajah)",
    "postal_code": "57462"
  },
  {
    "id": 3310042002,
    "province_id": 33,
    "regency_id": 3310,
    "district_id": 331004,
    "value": "Jambakan",
    "postal_code": "57462"
  },
  {
    "id": 3310042004,
    "province_id": 33,
    "regency_id": 3310,
    "district_id": 331004,
    "value": "Jarum",
    "postal_code": "57462"
  },
  {
    "id": 3310042016,
    "province_id": 33,
    "regency_id": 3310,
    "district_id": 331004,
    "value": "Jotangan",
    "postal_code": "57462"
  },
  {
    "id": 3310042015,
    "province_id": 33,
    "regency_id": 3310,
    "district_id": 331004,
    "value": "Kebon",
    "postal_code": "57462"
  },
  {
    "id": 3310042017,
    "province_id": 33,
    "regency_id": 3310,
    "district_id": 331004,
    "value": "Krakitan",
    "postal_code": "57462"
  },
  {
    "id": 3310042008,
    "province_id": 33,
    "regency_id": 3310,
    "district_id": 331004,
    "value": "Krikilan",
    "postal_code": "57462"
  },
  {
    "id": 3310042005,
    "province_id": 33,
    "regency_id": 3310,
    "district_id": 331004,
    "value": "Nengahan",
    "postal_code": "57462"
  },
  {
    "id": 3310042001,
    "province_id": 33,
    "regency_id": 3310,
    "district_id": 331004,
    "value": "Ngerangan",
    "postal_code": "57462"
  },
  {
    "id": 3310042007,
    "province_id": 33,
    "regency_id": 3310,
    "district_id": 331004,
    "value": "Paseban",
    "postal_code": "57462"
  },
  {
    "id": 3310042013,
    "province_id": 33,
    "regency_id": 3310,
    "district_id": 331004,
    "value": "Talang",
    "postal_code": "57462"
  },
  {
    "id": 3310042014,
    "province_id": 33,
    "regency_id": 3310,
    "district_id": 331004,
    "value": "Tawangrejo",
    "postal_code": "57462"
  },
  {
    "id": 3310042012,
    "province_id": 33,
    "regency_id": 3310,
    "district_id": 331004,
    "value": "Tegalrejo",
    "postal_code": "57462"
  },
  {
    "id": 3310042018,
    "province_id": 33,
    "regency_id": 3310,
    "district_id": 331004,
    "value": "Wiro",
    "postal_code": "57462"
  }
]