[
  {
    "id": 3203062002,
    "province_id": 32,
    "regency_id": 3203,
    "district_id": 320306,
    "value": "Bojongpicung",
    "postal_code": "43283"
  },
  {
    "id": 3203062004,
    "province_id": 32,
    "regency_id": 3203,
    "district_id": 320306,
    "value": "Cibarengkok",
    "postal_code": "43283"
  },
  {
    "id": 3203062009,
    "province_id": 32,
    "regency_id": 3203,
    "district_id": 320306,
    "value": "Cikondang",
    "postal_code": "43283"
  },
  {
    "id": 3203062001,
    "province_id": 32,
    "regency_id": 3203,
    "district_id": 320306,
    "value": "Hegarmanah",
    "postal_code": "43283"
  },
  {
    "id": 3203062008,
    "province_id": 32,
    "regency_id": 3203,
    "district_id": 320306,
    "value": "Jati",
    "postal_code": "43283"
  },
  {
    "id": 3203062014,
    "province_id": 32,
    "regency_id": 3203,
    "district_id": 320306,
    "value": "Jatisari",
    "postal_code": "43283"
  },
  {
    "id": 3203062006,
    "province_id": 32,
    "regency_id": 3203,
    "district_id": 320306,
    "value": "Kemang",
    "postal_code": "43283"
  },
  {
    "id": 3203062013,
    "province_id": 32,
    "regency_id": 3203,
    "district_id": 320306,
    "value": "Neglasari",
    "postal_code": "43283"
  },
  {
    "id": 3203062007,
    "province_id": 32,
    "regency_id": 3203,
    "district_id": 320306,
    "value": "Sukajaya",
    "postal_code": "43283"
  },
  {
    "id": 3203062010,
    "province_id": 32,
    "regency_id": 3203,
    "district_id": 320306,
    "value": "Sukarama",
    "postal_code": "43283"
  },
  {
    "id": 3203062012,
    "province_id": 32,
    "regency_id": 3203,
    "district_id": 320306,
    "value": "Sukaratu",
    "postal_code": "43283"
  }
]