[
  {
    "id": 9205212003,
    "province_id": 92,
    "regency_id": 9205,
    "district_id": 920521,
    "value": "Kaliam",
    "postal_code": "98493"
  },
  {
    "id": 9205212004,
    "province_id": 92,
    "regency_id": 9205,
    "district_id": 920521,
    "value": "Kalwal",
    "postal_code": "98493"
  },
  {
    "id": 9205212002,
    "province_id": 92,
    "regency_id": 9205,
    "district_id": 920521,
    "value": "Solol",
    "postal_code": "98493"
  },
  {
    "id": 9205212001,
    "province_id": 92,
    "regency_id": 9205,
    "district_id": 920521,
    "value": "Waibon",
    "postal_code": "98493"
  }
]