[
  {
    "id": 6309022002,
    "province_id": 63,
    "regency_id": 6309,
    "district_id": 630902,
    "value": "Ampukung",
    "postal_code": "71552"
  },
  {
    "id": 6309022012,
    "province_id": 63,
    "regency_id": 6309,
    "district_id": 630902,
    "value": "Bahungin",
    "postal_code": "71552"
  },
  {
    "id": 6309022005,
    "province_id": 63,
    "regency_id": 6309,
    "district_id": 630902,
    "value": "Binturu",
    "postal_code": "71552"
  },
  {
    "id": 6309022011,
    "province_id": 63,
    "regency_id": 6309,
    "district_id": 630902,
    "value": "Karangan Putih",
    "postal_code": "71552"
  },
  {
    "id": 6309022008,
    "province_id": 63,
    "regency_id": 6309,
    "district_id": 630902,
    "value": "Masintan",
    "postal_code": "71552"
  },
  {
    "id": 6309022010,
    "province_id": 63,
    "regency_id": 6309,
    "district_id": 630902,
    "value": "Paliat",
    "postal_code": "71552"
  },
  {
    "id": 6309022007,
    "province_id": 63,
    "regency_id": 6309,
    "district_id": 630902,
    "value": "Pasar Panas",
    "postal_code": "71552"
  },
  {
    "id": 6309022006,
    "province_id": 63,
    "regency_id": 6309,
    "district_id": 630902,
    "value": "Pudak Setegal (Pudak Stegal)",
    "postal_code": "71552"
  },
  {
    "id": 6309021001,
    "province_id": 63,
    "regency_id": 6309,
    "district_id": 630902,
    "value": "Pulau",
    "postal_code": "71552"
  },
  {
    "id": 6309022004,
    "province_id": 63,
    "regency_id": 6309,
    "district_id": 630902,
    "value": "Sei/Sungai Buluh",
    "postal_code": "71552"
  },
  {
    "id": 6309022009,
    "province_id": 63,
    "regency_id": 6309,
    "district_id": 630902,
    "value": "Takulat",
    "postal_code": "71552"
  },
  {
    "id": 6309022003,
    "province_id": 63,
    "regency_id": 6309,
    "district_id": 630902,
    "value": "Telaga Itar (Telagaitar)",
    "postal_code": "71552"
  }
]