[
  {
    "id": 3516032013,
    "province_id": 35,
    "regency_id": 3516,
    "district_id": 351603,
    "value": "Bendunganjati",
    "postal_code": "61374"
  },
  {
    "id": 3516032015,
    "province_id": 35,
    "regency_id": 3516,
    "district_id": 351603,
    "value": "Candiwatu",
    "postal_code": "61374"
  },
  {
    "id": 3516032009,
    "province_id": 35,
    "regency_id": 3516,
    "district_id": 351603,
    "value": "Cembor",
    "postal_code": "61374"
  },
  {
    "id": 3516032007,
    "province_id": 35,
    "regency_id": 3516,
    "district_id": 351603,
    "value": "Cempokolimo (Cepokolimo)",
    "postal_code": "61374"
  },
  {
    "id": 3516032008,
    "province_id": 35,
    "regency_id": 3516,
    "district_id": 351603,
    "value": "Claket",
    "postal_code": "61374"
  },
  {
    "id": 3516032011,
    "province_id": 35,
    "regency_id": 3516,
    "district_id": 351603,
    "value": "Kembangbelor",
    "postal_code": "61374"
  },
  {
    "id": 3516032001,
    "province_id": 35,
    "regency_id": 3516,
    "district_id": 351603,
    "value": "Kemiri",
    "postal_code": "61374"
  },
  {
    "id": 3516032003,
    "province_id": 35,
    "regency_id": 3516,
    "district_id": 351603,
    "value": "Kesimantengah",
    "postal_code": "61374"
  },
  {
    "id": 3516032019,
    "province_id": 35,
    "regency_id": 3516,
    "district_id": 351603,
    "value": "Kuripansari",
    "postal_code": "61374"
  },
  {
    "id": 3516032012,
    "province_id": 35,
    "regency_id": 3516,
    "district_id": 351603,
    "value": "Mojokembang",
    "postal_code": "61374"
  },
  {
    "id": 3516032010,
    "province_id": 35,
    "regency_id": 3516,
    "district_id": 351603,
    "value": "Nogosari",
    "postal_code": "61374"
  },
  {
    "id": 3516032005,
    "province_id": 35,
    "regency_id": 3516,
    "district_id": 351603,
    "value": "Pacet",
    "postal_code": "61374"
  },
  {
    "id": 3516032006,
    "province_id": 35,
    "regency_id": 3516,
    "district_id": 351603,
    "value": "Padusan",
    "postal_code": "61374"
  },
  {
    "id": 3516032020,
    "province_id": 35,
    "regency_id": 3516,
    "district_id": 351603,
    "value": "Pandanarum",
    "postal_code": "61374"
  },
  {
    "id": 3516032014,
    "province_id": 35,
    "regency_id": 3516,
    "district_id": 351603,
    "value": "Petak",
    "postal_code": "61374"
  },
  {
    "id": 3516032004,
    "province_id": 35,
    "regency_id": 3516,
    "district_id": 351603,
    "value": "Sajen",
    "postal_code": "61374"
  },
  {
    "id": 3516032018,
    "province_id": 35,
    "regency_id": 3516,
    "district_id": 351603,
    "value": "Sumberkembar",
    "postal_code": "61374"
  },
  {
    "id": 3516032017,
    "province_id": 35,
    "regency_id": 3516,
    "district_id": 351603,
    "value": "Tanjungkenongo",
    "postal_code": "61374"
  },
  {
    "id": 3516032016,
    "province_id": 35,
    "regency_id": 3516,
    "district_id": 351603,
    "value": "Warugunung",
    "postal_code": "61374"
  },
  {
    "id": 3516032002,
    "province_id": 35,
    "regency_id": 3516,
    "district_id": 351603,
    "value": "Wiyu",
    "postal_code": "61374"
  }
]