[
  {
    "id": 7203252002,
    "province_id": 72,
    "regency_id": 7203,
    "district_id": 720325,
    "value": "Alindau",
    "postal_code": "94343"
  },
  {
    "id": 7203252003,
    "province_id": 72,
    "regency_id": 7203,
    "district_id": 720325,
    "value": "Oti",
    "postal_code": "94343"
  },
  {
    "id": 7203252001,
    "province_id": 72,
    "regency_id": 7203,
    "district_id": 720325,
    "value": "Sikara Tobata",
    "postal_code": "94343"
  },
  {
    "id": 7203252006,
    "province_id": 72,
    "regency_id": 7203,
    "district_id": 720325,
    "value": "Sindosa",
    "postal_code": "94343"
  },
  {
    "id": 7203252005,
    "province_id": 72,
    "regency_id": 7203,
    "district_id": 720325,
    "value": "Sipeso",
    "postal_code": "94343"
  },
  {
    "id": 7203252004,
    "province_id": 72,
    "regency_id": 7203,
    "district_id": 720325,
    "value": "Tamarenja",
    "postal_code": "94343"
  }
]