[
  {
    "id": 3505102009,
    "province_id": 35,
    "regency_id": 3505,
    "district_id": 350510,
    "value": "Banggle",
    "postal_code": "66171"
  },
  {
    "id": 3505102004,
    "province_id": 35,
    "regency_id": 3505,
    "district_id": 350510,
    "value": "Gaprang",
    "postal_code": "66171"
  },
  {
    "id": 3505102003,
    "province_id": 35,
    "regency_id": 3505,
    "district_id": 350510,
    "value": "Gogodeso",
    "postal_code": "66171"
  },
  {
    "id": 3505102002,
    "province_id": 35,
    "regency_id": 3505,
    "district_id": 350510,
    "value": "Jatinom",
    "postal_code": "66171"
  },
  {
    "id": 3505101008,
    "province_id": 35,
    "regency_id": 3505,
    "district_id": 350510,
    "value": "Kanigoro",
    "postal_code": "66171"
  },
  {
    "id": 3505102007,
    "province_id": 35,
    "regency_id": 3505,
    "district_id": 350510,
    "value": "Karangsono",
    "postal_code": "66171"
  },
  {
    "id": 3505102012,
    "province_id": 35,
    "regency_id": 3505,
    "district_id": 350510,
    "value": "Kuningan",
    "postal_code": "66171"
  },
  {
    "id": 3505102001,
    "province_id": 35,
    "regency_id": 3505,
    "district_id": 350510,
    "value": "Minggirsari",
    "postal_code": "66171"
  },
  {
    "id": 3505102005,
    "province_id": 35,
    "regency_id": 3505,
    "district_id": 350510,
    "value": "Papungan",
    "postal_code": "66171"
  },
  {
    "id": 3505101010,
    "province_id": 35,
    "regency_id": 3505,
    "district_id": 350510,
    "value": "Satreyan",
    "postal_code": "66171"
  },
  {
    "id": 3505102011,
    "province_id": 35,
    "regency_id": 3505,
    "district_id": 350510,
    "value": "Sawentar",
    "postal_code": "66171"
  },
  {
    "id": 3505102006,
    "province_id": 35,
    "regency_id": 3505,
    "district_id": 350510,
    "value": "Tlogo",
    "postal_code": "66171"
  }
]